dsw/__init__.py
dsw/orbits.py
dsw/cepheid/__init__.py
dsw/cepheid/cepheid_template.py
dsw/cepheid/data/long_struc.fits
dsw/cepheid/data/short_struc.fits
dsw-0.1.14.dist-info/LICENSE-CC-BY-NC-SA
dsw-0.1.14.dist-info/METADATA
dsw-0.1.14.dist-info/WHEEL
dsw-0.1.14.dist-info/top_level.txt
dsw-0.1.14.dist-info/RECORD
