Metadata-Version: 2.1
Name: dsw
Version: 0.1.14
Summary: Tools used by Deep Sky Wonder
Home-page: https://github.com/DeepSkyWonder/dsw
Author: Cameron McEwing
Author-email: tech.mechanic@gmail.com
License: UNKNOWN
Platform: UNKNOWN
Classifier: Programming Language :: Python :: 3
Classifier: License :: OSI Approved :: MIT License
Classifier: Operating System :: OS Independent
Requires-Python: >=3.7
Requires-Dist: matplotlib
Requires-Dist: ipython
Requires-Dist: rebound (>=3.17.4)
Requires-Dist: numpy
Requires-Dist: astropy (>=4.3.1)
